labelary/__init__.py
labelary/convert.py
labelary_mwisslead-1.0.1.dist-info/LICENSE
labelary_mwisslead-1.0.1.dist-info/METADATA
labelary_mwisslead-1.0.1.dist-info/WHEEL
labelary_mwisslead-1.0.1.dist-info/top_level.txt
labelary_mwisslead-1.0.1.dist-info/RECORD
