Metadata-Version: 2.1
Name: labelary-mwisslead
Version: 1.0.1
Summary: Module for interacting with api.labelary.com
Home-page: https://github.com/mwisslead/pylabelary
Author: Michael Wisslead
Author-email: michael.wisslead@gmail.com
Maintainer: Michael Wisslead
Maintainer-email: michael.wisslead@gmail.com
License: (specified using classifiers)
Platform: (specified using classifiers)
Classifier: Programming Language :: Python
Classifier: License :: OSI Approved :: MIT License
Classifier: Operating System :: OS Independent
Requires-Dist: requests
